mew/__init__.py
mew/__version__.py
mew/convert_case.py
mew/decorator.py
mew/serializer.py
mew-0.1.4.dist-info/METADATA
mew-0.1.4.dist-info/WHEEL
mew-0.1.4.dist-info/top_level.txt
mew-0.1.4.dist-info/RECORD
