Metadata-Version: 2.1
Name: mew
Version: 0.1.4
Summary: Python dataclass serializer/deserializer
Home-page: http://github.com/cliffxuan/mew
Author: Cliff Xuan
Author-email: cliff.xuan@gmail.com
License: MIT
Platform: UNKNOWN
Classifier: Intended Audience :: Developers
Classifier: Natural Language :: English
Classifier: Programming Language :: Python
Classifier: Programming Language :: Python :: 3.6
Classifier: Programming Language :: Python :: 3.7
Classifier: Programming Language :: Python :: Implementation :: CPython
Requires-Python: >=3.6
Requires-Dist: pyyaml
Requires-Dist: backports-datetime-fromisoformat ; python_version < "3.7"
